{

    "images": [
        "assets/orig/pack.png"
    ],

    "frames": [
        [2, 888, 512, 512, 0, 0, 0],
        [2, 374, 512, 512, 0, 0, 0],
        [1664, 1664, 320, 320, 0, 0, 0],
        [2, 68, 172, 172, 0, 0, 0],
        [716, 961, 5, 17, 0, 0, 0],
        [516, 781, 108, 172, 0, 0, 0],
        [626, 901, 52, 52, 0, 0, 0],
        [783, 1181, 69, 91, 0, 0, 0]
    ],

    "animations": {
        "background": { "frames": [0] },
        "explosion": { "frames": [1] },
        "enemy3": { "frames": [2] },
        "enemy2": { "frames": [3] },
        "bullet": { "frames": [4] },
        "player": { "frames": [5] },
        "bang": { "frames": [6] },
        "enemy1": { "frames": [7] }
    }


}
